{"US Dollar":{"sell":"28000","buy":"27900"},"Euro":{"sell":"30480","buy":"30330"},"British Pound":{"sell":"36450","buy":"36250"},"Swiss Franc":{"sell":"29915","buy":"29765"},"Canadian Dollar":{"sell":"22215","buy":"22115"},"Australian Dollar":{"sell":"20830","buy":"20730"},"Swedish Krona":{"sell":"2960","buy":"2945"},"Norwegian Krone":{"sell":"3210","buy":"3195"},"Russian Ruble":{"sell":"328","buy":"325"},"Thai Baht":{"sell":"830","buy":"825"},"Singapore Dollar":{"sell":"20495","buy":"20395"},"Hong Kong Dollar":{"sell":"3570","buy":"3540"},"Azerbaijani Manat":{"sell":"16570","buy":"16470"},"Armenian Dram":{"sell":"585","buy":"580"},"Danish Krone":{"sell":"4100","buy":"4080"},"UAE Dirham":{"sell":"7620","buy":"7600"},"Japanese Yen":{"sell":"2240","buy":"2230"},"Turkish Lira":{"sell":"1900","buy":"1880"},"Chinese Yuan":{"sell":"4395","buy":"4375"},"KSA Riyal":{"sell":"7465","buy":"7435"},"Indian Rupee":{"sell":"368","buy":"366"},"Ringgit":{"sell":"6625","buy":"6595"},"Afghan Afghani":{"sell":"317","buy":"315"},"Kuwaiti Dinar":{"sell":"91820","buy":"91420"},"Iraqi Dinar":{"sell":"1920","buy":"1910"},"Bahraini Dinar":{"sell":"74325","buy":"73825"},"Omani Rial":{"sell":"72805","buy":"72505"},"Qatari Riyal":{"sell":"7690","buy":"7660"},"Azadi":{"sell":"13000000","buy":"12800000"},"Emami":{"sell":"13200000","buy":"13000000"},"\u00bd Azadi":{"sell":"7470000","buy":"7300000"},"\u00bc Azadi":{"sell":"4330000","buy":"4170000"},"Gerami":{"sell":"2650000","buy":"2520000"},"Gold Gram":{"sell":"1321852"},"Gold Mithqal":{"sell":"5726000"},"Gold Ounce":{"sell":"1942.71"},"Bitcoin":{"sell":"42159.84"}}
