{"US Dollar":{"sell":"27800","buy":"27700"},"Euro":{"sell":"29810","buy":"29660"},"British Pound":{"sell":"35330","buy":"35130"},"Swiss Franc":{"sell":"28995","buy":"28845"},"Canadian Dollar":{"sell":"21785","buy":"21685"},"Australian Dollar":{"sell":"19875","buy":"19775"},"Swedish Krona":{"sell":"2880","buy":"2865"},"Norwegian Krone":{"sell":"3070","buy":"3055"},"Russian Ruble":{"sell":"376","buy":"373"},"Thai Baht":{"sell":"815","buy":"810"},"Singapore Dollar":{"sell":"20210","buy":"20110"},"Hong Kong Dollar":{"sell":"3540","buy":"3510"},"Azerbaijani Manat":{"sell":"16325","buy":"16225"},"Armenian Dram":{"sell":"595","buy":"590"},"Danish Krone":{"sell":"4005","buy":"3985"},"UAE Dirham":{"sell":"7570","buy":"7550"},"Japanese Yen":{"sell":"2170","buy":"2160"},"Turkish Lira":{"sell":"1880","buy":"1860"},"Chinese Yuan":{"sell":"4225","buy":"4205"},"KSA Riyal":{"sell":"7410","buy":"7380"},"Indian Rupee":{"sell":"362","buy":"360"},"Ringgit":{"sell":"6380","buy":"6350"},"Afghan Afghani":{"sell":"320","buy":"318"},"Kuwaiti Dinar":{"sell":"90920","buy":"90520"},"Iraqi Dinar":{"sell":"1905","buy":"1895"},"Bahraini Dinar":{"sell":"73730","buy":"73230"},"Omani Rial":{"sell":"72195","buy":"71895"},"Qatari Riyal":{"sell":"7635","buy":"7605"},"Azadi":{"sell":"12600000","buy":"12300000"},"Emami":{"sell":"13020000","buy":"12800000"},"\u00bd Azadi":{"sell":"7200000","buy":"7000000"},"\u00bc Azadi":{"sell":"4230000","buy":"4050000"},"Gerami":{"sell":"2570000","buy":"2450000"},"Gold Gram":{"sell":"1278452"},"Gold Mithqal":{"sell":"5538000"},"Gold Ounce":{"sell":"1900.44"},"Bitcoin":{"sell":"38904.0"}}
