{"US Dollar":{"sell":"29820","buy":"29720"},"Euro":{"sell":"29870","buy":"29720"},"British Pound":{"sell":"34530","buy":"34330"},"Swiss Franc":{"sell":"30495","buy":"30345"},"Canadian Dollar":{"sell":"22665","buy":"22565"},"Australian Dollar":{"sell":"20360","buy":"20260"},"Swedish Krona":{"sell":"2780","buy":"2765"},"Norwegian Krone":{"sell":"2980","buy":"2965"},"Russian Ruble":{"sell":"493","buy":"493"},"Thai Baht":{"sell":"810","buy":"805"},"Singapore Dollar":{"sell":"21320","buy":"21220"},"Hong Kong Dollar":{"sell":"3800","buy":"3770"},"Azerbaijani Manat":{"sell":"17510","buy":"17410"},"Armenian Dram":{"sell":"735","buy":"730"},"Danish Krone":{"sell":"4015","buy":"3995"},"UAE Dirham":{"sell":"8120","buy":"8100"},"Japanese Yen":{"sell":"2140","buy":"2130"},"Turkish Lira":{"sell":"1640","buy":"1620"},"Chinese Yuan":{"sell":"4320","buy":"4300"},"KSA Riyal":{"sell":"7930","buy":"7900"},"Indian Rupee":{"sell":"374","buy":"372"},"Ringgit":{"sell":"6655","buy":"6625"},"Afghan Afghani":{"sell":"337","buy":"335"},"Kuwaiti Dinar":{"sell":"96745","buy":"96345"},"Iraqi Dinar":{"sell":"2040","buy":"2030"},"Bahraini Dinar":{"sell":"79105","buy":"78605"},"Omani Rial":{"sell":"77555","buy":"77255"},"Qatari Riyal":{"sell":"8190","buy":"8160"},"Azadi":{"sell":"13000000","buy":"12700000"},"Emami":{"sell":"13700000","buy":"13500000"},"\u00bd Azadi":{"sell":"7950000","buy":"7700000"},"\u00bc Azadi":{"sell":"4950000","buy":"4750000"},"Gerami":{"sell":"2950000","buy":"2800000"},"Gold Gram":{"sell":"1255828"},"Gold Mithqal":{"sell":"5440000"},"Gold Ounce":{"sell":"1701.05"},"Bitcoin":{"sell":"19944.59"}}
