{"US Dollar":{"sell":"31750","buy":"31650"},"Euro":{"sell":"31715","buy":"31565"},"British Pound":{"sell":"36525","buy":"36325"},"Swiss Franc":{"sell":"33115","buy":"32965"},"Canadian Dollar":{"sell":"24115","buy":"24015"},"Australian Dollar":{"sell":"21390","buy":"21290"},"Swedish Krona":{"sell":"2965","buy":"2950"},"Norwegian Krone":{"sell":"3145","buy":"3130"},"Russian Ruble":{"sell":"530","buy":"530"},"Thai Baht":{"sell":"865","buy":"860"},"Singapore Dollar":{"sell":"22575","buy":"22475"},"Hong Kong Dollar":{"sell":"4045","buy":"4015"},"Azerbaijani Manat":{"sell":"18685","buy":"18585"},"Armenian Dram":{"sell":"780","buy":"775"},"Danish Krone":{"sell":"4265","buy":"4245"},"UAE Dirham":{"sell":"8645","buy":"8625"},"Japanese Yen":{"sell":"2215","buy":"2205"},"Turkish Lira":{"sell":"1740","buy":"1720"},"Chinese Yuan":{"sell":"4545","buy":"4525"},"KSA Riyal":{"sell":"8445","buy":"8415"},"Indian Rupee":{"sell":"398","buy":"396"},"Ringgit":{"sell":"7000","buy":"6970"},"Afghan Afghani":{"sell":"358","buy":"356"},"Kuwaiti Dinar":{"sell":"102760","buy":"102360"},"Iraqi Dinar":{"sell":"2170","buy":"2160"},"Bahraini Dinar":{"sell":"84220","buy":"83720"},"Omani Rial":{"sell":"82465","buy":"82165"},"Qatari Riyal":{"sell":"8720","buy":"8690"},"Azadi":{"sell":"13600000","buy":"13250000"},"Emami":{"sell":"14450000","buy":"14100000"},"\u00bd Azadi":{"sell":"8150000","buy":"7900000"},"\u00bc Azadi":{"sell":"5150000","buy":"4950000"},"Gerami":{"sell":"3050000","buy":"2900000"},"Gold Gram":{"sell":"1328546"},"Gold Mithqal":{"sell":"5755000"},"Gold Ounce":{"sell":"1687.62"},"Bitcoin":{"sell":"20141.99"}}
