{"US Dollar":{"sell":"29820","buy":"29720"},"Euro":{"sell":"29700","buy":"29550"},"British Pound":{"sell":"34435","buy":"34235"},"Swiss Franc":{"sell":"30400","buy":"30250"},"Canadian Dollar":{"sell":"22660","buy":"22560"},"Australian Dollar":{"sell":"20240","buy":"20140"},"Swedish Krona":{"sell":"2765","buy":"2750"},"Norwegian Krone":{"sell":"2970","buy":"2955"},"Russian Ruble":{"sell":"495","buy":"495"},"Thai Baht":{"sell":"810","buy":"805"},"Singapore Dollar":{"sell":"21270","buy":"21170"},"Hong Kong Dollar":{"sell":"3800","buy":"3770"},"Azerbaijani Manat":{"sell":"17520","buy":"17420"},"Armenian Dram":{"sell":"735","buy":"730"},"Danish Krone":{"sell":"3995","buy":"3975"},"UAE Dirham":{"sell":"8120","buy":"8100"},"Japanese Yen":{"sell":"2125","buy":"2115"},"Turkish Lira":{"sell":"1635","buy":"1615"},"Chinese Yuan":{"sell":"4320","buy":"4300"},"KSA Riyal":{"sell":"7935","buy":"7905"},"Indian Rupee":{"sell":"374","buy":"372"},"Ringgit":{"sell":"6650","buy":"6620"},"Afghan Afghani":{"sell":"335","buy":"333"},"Kuwaiti Dinar":{"sell":"96695","buy":"96295"},"Iraqi Dinar":{"sell":"2030","buy":"2020"},"Bahraini Dinar":{"sell":"79095","buy":"78595"},"Omani Rial":{"sell":"77455","buy":"77155"},"Qatari Riyal":{"sell":"8190","buy":"8160"},"Azadi":{"sell":"13000000","buy":"12700000"},"Emami":{"sell":"13700000","buy":"13500000"},"\u00bd Azadi":{"sell":"7950000","buy":"7700000"},"\u00bc Azadi":{"sell":"4950000","buy":"4750000"},"Gerami":{"sell":"2950000","buy":"2800000"},"Gold Gram":{"sell":"1254674"},"Gold Mithqal":{"sell":"5435000"},"Gold Ounce":{"sell":"1700.17"},"Bitcoin":{"sell":"20087.23"}}
