{"US Dollar":{"sell":"39650","buy":"39550"},"Euro":{"sell":"42055","buy":"41905"},"British Pound":{"sell":"47985","buy":"47785"},"Swiss Franc":{"sell":"42800","buy":"42650"},"Canadian Dollar":{"sell":"29095","buy":"28995"},"Australian Dollar":{"sell":"26495","buy":"26395"},"Swedish Krona":{"sell":"3800","buy":"3785"},"Norwegian Krone":{"sell":"4030","buy":"4015"},"Russian Ruble":{"sell":"555","buy":"550"},"Thai Baht":{"sell":"1140","buy":"1135"},"Singapore Dollar":{"sell":"29315","buy":"29215"},"Hong Kong Dollar":{"sell":"5085","buy":"5055"},"Azerbaijani Manat":{"sell":"23175","buy":"23075"},"Armenian Dram":{"sell":"1005","buy":"1000"},"Danish Krone":{"sell":"5655","buy":"5635"},"UAE Dirham":{"sell":"10795","buy":"10775"},"Japanese Yen":{"sell":"3005","buy":"2995"},"Turkish Lira":{"sell":"2125","buy":"2105"},"Chinese Yuan":{"sell":"5685","buy":"5665"},"KSA Riyal":{"sell":"10540","buy":"10510"},"Indian Rupee":{"sell":"478","buy":"476"},"Ringgit":{"sell":"8935","buy":"8905"},"Afghan Afghani":{"sell":"450","buy":"448"},"Kuwaiti Dinar":{"sell":"129445","buy":"129045"},"Iraqi Dinar":{"sell":"2710","buy":"2700"},"Bahraini Dinar":{"sell":"105170","buy":"104670"},"Omani Rial":{"sell":"103125","buy":"102825"},"Qatari Riyal":{"sell":"10890","buy":"10860"},"Azadi":{"sell":"18150000","buy":"17800000"},"Emami":{"sell":"18700000","buy":"18500000"},"\u00bd Azadi":{"sell":"12000000","buy":"11700000"},"\u00bc Azadi":{"sell":"8950000","buy":"8700000"},"Gerami":{"sell":"4100000","buy":"3900000"},"Gold Gram":{"sell":"1770626"},"Gold Mithqal":{"sell":"7670000"},"Gold Ounce":{"sell":"1818.23"},"Bitcoin":{"sell":"16838.22"}}
