{"US Dollar":{"sell":"39200","buy":"39100"},"Euro":{"sell":"41550","buy":"41400"},"British Pound":{"sell":"47600","buy":"47400"},"Swiss Franc":{"sell":"42065","buy":"41915"},"Canadian Dollar":{"sell":"28520","buy":"28420"},"Australian Dollar":{"sell":"26205","buy":"26105"},"Swedish Krona":{"sell":"3765","buy":"3750"},"Norwegian Krone":{"sell":"3960","buy":"3945"},"Russian Ruble":{"sell":"605","buy":"600"},"Thai Baht":{"sell":"1125","buy":"1120"},"Singapore Dollar":{"sell":"28845","buy":"28745"},"Hong Kong Dollar":{"sell":"5035","buy":"5005"},"Azerbaijani Manat":{"sell":"23005","buy":"22905"},"Armenian Dram":{"sell":"990","buy":"985"},"Danish Krone":{"sell":"5580","buy":"5560"},"UAE Dirham":{"sell":"10670","buy":"10650"},"Japanese Yen":{"sell":"2865","buy":"2855"},"Turkish Lira":{"sell":"2105","buy":"2085"},"Chinese Yuan":{"sell":"5620","buy":"5600"},"KSA Riyal":{"sell":"10425","buy":"10395"},"Indian Rupee":{"sell":"473","buy":"471"},"Ringgit":{"sell":"8860","buy":"8830"},"Afghan Afghani":{"sell":"447","buy":"445"},"Kuwaiti Dinar":{"sell":"127755","buy":"127355"},"Iraqi Dinar":{"sell":"2675","buy":"2665"},"Bahraini Dinar":{"sell":"104135","buy":"103635"},"Omani Rial":{"sell":"101970","buy":"101670"},"Qatari Riyal":{"sell":"10765","buy":"10735"},"Azadi":{"sell":"18250000","buy":"17900000"},"Emami":{"sell":"19350000","buy":"19000000"},"\u00bd Azadi":{"sell":"12050000","buy":"11700000"},"\u00bc Azadi":{"sell":"9050000","buy":"8700000"},"Gerami":{"sell":"4200000","buy":"4000000"},"Gold Gram":{"sell":"1727918"},"Gold Mithqal":{"sell":"7485000"},"Gold Ounce":{"sell":"1793.12"},"Bitcoin":{"sell":"16695.69"}}
