{"US Dollar":{"sell":"39330","buy":"39230"},"Euro":{"sell":"41720","buy":"41570"},"British Pound":{"sell":"47870","buy":"47670"},"Swiss Franc":{"sell":"42165","buy":"42015"},"Canadian Dollar":{"sell":"28760","buy":"28660"},"Australian Dollar":{"sell":"26380","buy":"26280"},"Swedish Krona":{"sell":"3790","buy":"3775"},"Norwegian Krone":{"sell":"3985","buy":"3970"},"Russian Ruble":{"sell":"600","buy":"595"},"Thai Baht":{"sell":"1130","buy":"1125"},"Singapore Dollar":{"sell":"28965","buy":"28865"},"Hong Kong Dollar":{"sell":"5055","buy":"5025"},"Azerbaijani Manat":{"sell":"23070","buy":"22970"},"Armenian Dram":{"sell":"990","buy":"985"},"Danish Krone":{"sell":"5610","buy":"5590"},"UAE Dirham":{"sell":"10710","buy":"10690"},"Japanese Yen":{"sell":"2890","buy":"2880"},"Turkish Lira":{"sell":"2110","buy":"2090"},"Chinese Yuan":{"sell":"5630","buy":"5610"},"KSA Riyal":{"sell":"10460","buy":"10430"},"Indian Rupee":{"sell":"475","buy":"473"},"Ringgit":{"sell":"8890","buy":"8860"},"Afghan Afghani":{"sell":"448","buy":"446"},"Kuwaiti Dinar":{"sell":"128175","buy":"127775"},"Iraqi Dinar":{"sell":"2685","buy":"2675"},"Bahraini Dinar":{"sell":"104545","buy":"104045"},"Omani Rial":{"sell":"102385","buy":"102085"},"Qatari Riyal":{"sell":"10800","buy":"10770"},"Azadi":{"sell":"18200000","buy":"17900000"},"Emami":{"sell":"19450000","buy":"19100000"},"\u00bd Azadi":{"sell":"12050000","buy":"11650000"},"\u00bc Azadi":{"sell":"9050000","buy":"8650000"},"Gerami":{"sell":"4200000","buy":"4000000"},"Gold Gram":{"sell":"1743385"},"Gold Mithqal":{"sell":"7552000"},"Gold Ounce":{"sell":"1791.95"},"Bitcoin":{"sell":"16743.23"}}
