{"US Dollar":{"sell":"34460","buy":"34360"},"Euro":{"sell":"34090","buy":"33940"},"British Pound":{"sell":"39595","buy":"39395"},"Swiss Franc":{"sell":"34555","buy":"34405"},"Canadian Dollar":{"sell":"25340","buy":"25240"},"Australian Dollar":{"sell":"22145","buy":"22045"},"Swedish Krona":{"sell":"3130","buy":"3115"},"Norwegian Krone":{"sell":"3335","buy":"3320"},"Russian Ruble":{"sell":"560","buy":"555"},"Thai Baht":{"sell":"915","buy":"910"},"Singapore Dollar":{"sell":"24410","buy":"24310"},"Hong Kong Dollar":{"sell":"4390","buy":"4360"},"Azerbaijani Manat":{"sell":"20180","buy":"20080"},"Armenian Dram":{"sell":"850","buy":"845"},"Danish Krone":{"sell":"4580","buy":"4560"},"UAE Dirham":{"sell":"9380","buy":"9360"},"Japanese Yen":{"sell":"2340","buy":"2330"},"Turkish Lira":{"sell":"1850","buy":"1830"},"Chinese Yuan":{"sell":"4735","buy":"4715"},"KSA Riyal":{"sell":"9170","buy":"9140"},"Indian Rupee":{"sell":"416","buy":"414"},"Ringgit":{"sell":"7275","buy":"7245"},"Afghan Afghani":{"sell":"387","buy":"385"},"Kuwaiti Dinar":{"sell":"111235","buy":"110835"},"Iraqi Dinar":{"sell":"2350","buy":"2340"},"Bahraini Dinar":{"sell":"91440","buy":"90940"},"Omani Rial":{"sell":"89495","buy":"89195"},"Qatari Riyal":{"sell":"9465","buy":"9435"},"Azadi":{"sell":"15050000","buy":"14700000"},"Emami":{"sell":"16050000","buy":"15700000"},"\u00bd Azadi":{"sell":"8550000","buy":"8300000"},"\u00bc Azadi":{"sell":"5550000","buy":"5300000"},"Gerami":{"sell":"3250000","buy":"3050000"},"Gold Gram":{"sell":"1401264"},"Gold Mithqal":{"sell":"6070000"},"Gold Ounce":{"sell":"1655.22"},"Bitcoin":{"sell":"20390.79"}}
