{"US Dollar":{"sell":"36270","buy":"36170"},"Euro":{"sell":"38060","buy":"37910"},"British Pound":{"sell":"44310","buy":"44110"},"Swiss Franc":{"sell":"38540","buy":"38390"},"Canadian Dollar":{"sell":"27010","buy":"26910"},"Australian Dollar":{"sell":"24690","buy":"24590"},"Swedish Krona":{"sell":"3505","buy":"3490"},"Norwegian Krone":{"sell":"3715","buy":"3700"},"Russian Ruble":{"sell":"590","buy":"585"},"Thai Baht":{"sell":"1040","buy":"1035"},"Singapore Dollar":{"sell":"26755","buy":"26655"},"Hong Kong Dollar":{"sell":"4660","buy":"4630"},"Azerbaijani Manat":{"sell":"21105","buy":"21005"},"Armenian Dram":{"sell":"915","buy":"910"},"Danish Krone":{"sell":"5115","buy":"5095"},"UAE Dirham":{"sell":"9875","buy":"9855"},"Japanese Yen":{"sell":"2665","buy":"2655"},"Turkish Lira":{"sell":"1945","buy":"1925"},"Chinese Yuan":{"sell":"5130","buy":"5110"},"KSA Riyal":{"sell":"9645","buy":"9615"},"Indian Rupee":{"sell":"446","buy":"444"},"Ringgit":{"sell":"8235","buy":"8205"},"Afghan Afghani":{"sell":"410","buy":"408"},"Kuwaiti Dinar":{"sell":"118180","buy":"117780"},"Iraqi Dinar":{"sell":"2485","buy":"2475"},"Bahraini Dinar":{"sell":"96215","buy":"95715"},"Omani Rial":{"sell":"94205","buy":"93905"},"Qatari Riyal":{"sell":"9960","buy":"9930"},"Azadi":{"sell":"16600000","buy":"16300000"},"Emami":{"sell":"17340000","buy":"17120000"},"\u00bd Azadi":{"sell":"9530000","buy":"9350000"},"\u00bc Azadi":{"sell":"6530000","buy":"6350000"},"Gerami":{"sell":"3500000","buy":"3400000"},"Gold Gram":{"sell":"1577865"},"Gold Mithqal":{"sell":"6835000"},"Gold Ounce":{"sell":"1802.28"},"Bitcoin":{"sell":"17106.3"}}
