{"US Dollar":{"sell":"26230","buy":"26130"},"Euro":{"sell":"29390","buy":"29240"},"British Pound":{"sell":"35130","buy":"34930"},"Swiss Franc":{"sell":"28455","buy":"28305"},"Canadian Dollar":{"sell":"20565","buy":"20465"},"Australian Dollar":{"sell":"18930","buy":"18830"},"Swedish Krona":{"sell":"2770","buy":"2755"},"Norwegian Krone":{"sell":"2950","buy":"2935"},"Russian Ruble":{"sell":"314","buy":"311"},"Thai Baht":{"sell":"805","buy":"800"},"Singapore Dollar":{"sell":"19320","buy":"19220"},"Hong Kong Dollar":{"sell":"3355","buy":"3325"},"Azerbaijani Manat":{"sell":"15445","buy":"15345"},"Armenian Dram":{"sell":"545","buy":"540"},"Danish Krone":{"sell":"3950","buy":"3930"},"UAE Dirham":{"sell":"7140","buy":"7120"},"Japanese Yen":{"sell":"2270","buy":"2260"},"Turkish Lira":{"sell":"1900","buy":"1880"},"Chinese Yuan":{"sell":"4160","buy":"4140"},"KSA Riyal":{"sell":"6990","buy":"6960"},"Indian Rupee":{"sell":"348","buy":"346"},"Ringgit":{"sell":"6245","buy":"6215"},"Afghan Afghani":{"sell":"285","buy":"283"},"Kuwaiti Dinar":{"sell":"86555","buy":"86155"},"Iraqi Dinar":{"sell":"1795","buy":"1785"},"Bahraini Dinar":{"sell":"69565","buy":"69065"},"Omani Rial":{"sell":"68220","buy":"67920"},"Qatari Riyal":{"sell":"7205","buy":"7175"},"Azadi":{"sell":"11850000","buy":"11600000"},"Emami":{"sell":"12020000","buy":"11890000"},"\u00bd Azadi":{"sell":"6850000","buy":"6730000"},"\u00bc Azadi":{"sell":"3850000","buy":"3750000"},"Gerami":{"sell":"2350000","buy":"2250000"},"Gold Gram":{"sell":"1203887"},"Gold Mithqal":{"sell":"5215000"},"Gold Ounce":{"sell":"1905.77"},"Bitcoin":{"sell":"38512.31"}}
