{"US Dollar":{"sell":"38450","buy":"38350"},"Euro":{"sell":"40835","buy":"40685"},"British Pound":{"sell":"47440","buy":"47240"},"Swiss Franc":{"sell":"41385","buy":"41235"},"Canadian Dollar":{"sell":"28320","buy":"28220"},"Australian Dollar":{"sell":"26040","buy":"25940"},"Swedish Krona":{"sell":"3745","buy":"3730"},"Norwegian Krone":{"sell":"3920","buy":"3905"},"Russian Ruble":{"sell":"600","buy":"595"},"Thai Baht":{"sell":"1100","buy":"1095"},"Singapore Dollar":{"sell":"28375","buy":"28275"},"Hong Kong Dollar":{"sell":"4945","buy":"4915"},"Azerbaijani Manat":{"sell":"22870","buy":"22770"},"Armenian Dram":{"sell":"970","buy":"965"},"Danish Krone":{"sell":"5490","buy":"5470"},"UAE Dirham":{"sell":"10470","buy":"10450"},"Japanese Yen":{"sell":"2815","buy":"2805"},"Turkish Lira":{"sell":"2060","buy":"2040"},"Chinese Yuan":{"sell":"5510","buy":"5490"},"KSA Riyal":{"sell":"10230","buy":"10200"},"Indian Rupee":{"sell":"464","buy":"462"},"Ringgit":{"sell":"8705","buy":"8675"},"Afghan Afghani":{"sell":"444","buy":"442"},"Kuwaiti Dinar":{"sell":"125410","buy":"125010"},"Iraqi Dinar":{"sell":"2635","buy":"2625"},"Bahraini Dinar":{"sell":"102005","buy":"101505"},"Omani Rial":{"sell":"99870","buy":"99570"},"Qatari Riyal":{"sell":"10560","buy":"10530"},"Azadi":{"sell":"17850000","buy":"17500000"},"Emami":{"sell":"18900000","buy":"18600000"},"\u00bd Azadi":{"sell":"11900000","buy":"11550000"},"\u00bc Azadi":{"sell":"8900000","buy":"8550000"},"Gerami":{"sell":"4200000","buy":"4000000"},"Gold Gram":{"sell":"1692136"},"Gold Mithqal":{"sell":"7330000"},"Gold Ounce":{"sell":"1777.95"},"Bitcoin":{"sell":"17691.47"}}
