{"US Dollar":{"sell":"39500","buy":"39400"},"Euro":{"sell":"41955","buy":"41805"},"British Pound":{"sell":"48255","buy":"48055"},"Swiss Franc":{"sell":"42465","buy":"42315"},"Canadian Dollar":{"sell":"28950","buy":"28850"},"Australian Dollar":{"sell":"26545","buy":"26445"},"Swedish Krona":{"sell":"3815","buy":"3800"},"Norwegian Krone":{"sell":"4005","buy":"3990"},"Russian Ruble":{"sell":"595","buy":"590"},"Thai Baht":{"sell":"1135","buy":"1130"},"Singapore Dollar":{"sell":"29130","buy":"29030"},"Hong Kong Dollar":{"sell":"5075","buy":"5045"},"Azerbaijani Manat":{"sell":"23200","buy":"23100"},"Armenian Dram":{"sell":"995","buy":"990"},"Danish Krone":{"sell":"5640","buy":"5620"},"UAE Dirham":{"sell":"10755","buy":"10735"},"Japanese Yen":{"sell":"2900","buy":"2890"},"Turkish Lira":{"sell":"2115","buy":"2095"},"Chinese Yuan":{"sell":"5665","buy":"5645"},"KSA Riyal":{"sell":"10500","buy":"10470"},"Indian Rupee":{"sell":"477","buy":"475"},"Ringgit":{"sell":"8925","buy":"8895"},"Afghan Afghani":{"sell":"450","buy":"448"},"Kuwaiti Dinar":{"sell":"128890","buy":"128490"},"Iraqi Dinar":{"sell":"2700","buy":"2690"},"Bahraini Dinar":{"sell":"104770","buy":"104270"},"Omani Rial":{"sell":"102735","buy":"102435"},"Qatari Riyal":{"sell":"10850","buy":"10820"},"Azadi":{"sell":"18200000","buy":"17900000"},"Emami":{"sell":"19450000","buy":"19100000"},"\u00bd Azadi":{"sell":"12050000","buy":"11650000"},"\u00bc Azadi":{"sell":"9050000","buy":"8650000"},"Gerami":{"sell":"4200000","buy":"4000000"},"Gold Gram":{"sell":"1762546"},"Gold Mithqal":{"sell":"7635000"},"Gold Ounce":{"sell":"1796.12"},"Bitcoin":{"sell":"16761.77"}}
