{"US Dollar":{"sell":"31150","buy":"31050"},"Euro":{"sell":"32625","buy":"32475"},"British Pound":{"sell":"37835","buy":"37635"},"Swiss Franc":{"sell":"32640","buy":"32490"},"Canadian Dollar":{"sell":"24210","buy":"24110"},"Australian Dollar":{"sell":"21440","buy":"21340"},"Swedish Krona":{"sell":"3055","buy":"3040"},"Norwegian Krone":{"sell":"3155","buy":"3140"},"Russian Ruble":{"sell":"570","buy":"570"},"Thai Baht":{"sell":"885","buy":"880"},"Singapore Dollar":{"sell":"22375","buy":"22275"},"Hong Kong Dollar":{"sell":"3970","buy":"3940"},"Azerbaijani Manat":{"sell":"18385","buy":"18285"},"Armenian Dram":{"sell":"760","buy":"755"},"Danish Krone":{"sell":"4385","buy":"4365"},"UAE Dirham":{"sell":"8480","buy":"8460"},"Japanese Yen":{"sell":"2280","buy":"2270"},"Turkish Lira":{"sell":"1870","buy":"1850"},"Chinese Yuan":{"sell":"4650","buy":"4630"},"KSA Riyal":{"sell":"8300","buy":"8270"},"Indian Rupee":{"sell":"394","buy":"392"},"Ringgit":{"sell":"7080","buy":"7050"},"Afghan Afghani":{"sell":"353","buy":"351"},"Kuwaiti Dinar":{"sell":"101570","buy":"101170"},"Iraqi Dinar":{"sell":"2135","buy":"2125"},"Bahraini Dinar":{"sell":"82610","buy":"82110"},"Omani Rial":{"sell":"80905","buy":"80605"},"Qatari Riyal":{"sell":"8555","buy":"8525"},"Azadi":{"sell":"13950000","buy":"13650000"},"Emami":{"sell":"14900000","buy":"14550000"},"\u00bd Azadi":{"sell":"7980000","buy":"7750000"},"\u00bc Azadi":{"sell":"4980000","buy":"4700000"},"Gerami":{"sell":"3000000","buy":"2850000"},"Gold Gram":{"sell":"1384874"},"Gold Mithqal":{"sell":"5999000"},"Gold Ounce":{"sell":"1818.45"},"Bitcoin":{"sell":"20178.12"}}
