{"US Dollar":{"sell":"39710","buy":"39610"},"Euro":{"sell":"41875","buy":"41725"},"British Pound":{"sell":"47335","buy":"47135"},"Swiss Franc":{"sell":"42360","buy":"42210"},"Canadian Dollar":{"sell":"29160","buy":"29060"},"Australian Dollar":{"sell":"26680","buy":"26580"},"Swedish Krona":{"sell":"3765","buy":"3750"},"Norwegian Krone":{"sell":"3995","buy":"3980"},"Russian Ruble":{"sell":"545","buy":"540"},"Thai Baht":{"sell":"1155","buy":"1150"},"Singapore Dollar":{"sell":"29545","buy":"29445"},"Hong Kong Dollar":{"sell":"5080","buy":"5050"},"Azerbaijani Manat":{"sell":"23335","buy":"23235"},"Armenian Dram":{"sell":"1005","buy":"1000"},"Danish Krone":{"sell":"5630","buy":"5610"},"UAE Dirham":{"sell":"10810","buy":"10790"},"Japanese Yen":{"sell":"3045","buy":"3035"},"Turkish Lira":{"sell":"2120","buy":"2100"},"Chinese Yuan":{"sell":"5750","buy":"5730"},"KSA Riyal":{"sell":"10560","buy":"10530"},"Indian Rupee":{"sell":"479","buy":"479"},"Ringgit":{"sell":"9010","buy":"8980"},"Afghan Afghani":{"sell":"444","buy":"439"},"Kuwaiti Dinar":{"sell":"129665","buy":"129265"},"Iraqi Dinar":{"sell":"2715","buy":"2705"},"Bahraini Dinar":{"sell":"105350","buy":"104850"},"Omani Rial":{"sell":"103150","buy":"102850"},"Qatari Riyal":{"sell":"10905","buy":"10875"},"Azadi":{"sell":"19000000","buy":"18500000"},"Emami":{"sell":"20450000","buy":"19750000"},"\u00bd Azadi":{"sell":"12000000","buy":"11400000"},"\u00bc Azadi":{"sell":"8700000","buy":"8100000"},"Gerami":{"sell":"4400000","buy":"4100000"},"Gold Gram":{"sell":"1790248"},"Gold Mithqal":{"sell":"7755000"},"Gold Ounce":{"sell":"1838.52"},"Bitcoin":{"sell":"16736.95"}}
