{"US Dollar":{"sell":"42000","buy":"41900"},"Euro":{"sell":"44800","buy":"44650"},"British Pound":{"sell":"50605","buy":"50405"},"Swiss Franc":{"sell":"45465","buy":"45315"},"Canadian Dollar":{"sell":"31030","buy":"30930"},"Australian Dollar":{"sell":"28540","buy":"28440"},"Swedish Krona":{"sell":"4025","buy":"4010"},"Norwegian Krone":{"sell":"4265","buy":"4250"},"Russian Ruble":{"sell":"575","buy":"570"},"Thai Baht":{"sell":"1215","buy":"1210"},"Singapore Dollar":{"sell":"31325","buy":"31225"},"Hong Kong Dollar":{"sell":"5385","buy":"5355"},"Azerbaijani Manat":{"sell":"24645","buy":"24545"},"Armenian Dram":{"sell":"1065","buy":"1060"},"Danish Krone":{"sell":"6025","buy":"6005"},"UAE Dirham":{"sell":"11435","buy":"11415"},"Japanese Yen":{"sell":"3185","buy":"3175"},"Turkish Lira":{"sell":"2245","buy":"2225"},"Chinese Yuan":{"sell":"6090","buy":"6070"},"KSA Riyal":{"sell":"11175","buy":"11145"},"Indian Rupee":{"sell":"505","buy":"505"},"Ringgit":{"sell":"9535","buy":"9505"},"Afghan Afghani":{"sell":"470","buy":"465"},"Kuwaiti Dinar":{"sell":"137230","buy":"136830"},"Iraqi Dinar":{"sell":"2875","buy":"2865"},"Bahraini Dinar":{"sell":"111390","buy":"110890"},"Omani Rial":{"sell":"109080","buy":"108780"},"Qatari Riyal":{"sell":"11535","buy":"11505"},"Azadi":{"sell":"21000000","buy":"20000000"},"Emami":{"sell":"23000000","buy":"22500000"},"\u00bd Azadi":{"sell":"13000000","buy":"12700000"},"\u00bc Azadi":{"sell":"10000000","buy":"9600000"},"Gerami":{"sell":"4700000","buy":"4300000"},"Gold Gram":{"sell":"1920679"},"Gold Mithqal":{"sell":"8320000"},"Gold Ounce":{"sell":"1821.3"},"Bitcoin":{"sell":"16463.14"}}
