{"US Dollar":{"sell":"45100","buy":"45000"},"Euro":{"sell":"49055","buy":"48905"},"British Pound":{"sell":"55875","buy":"55675"},"Swiss Franc":{"sell":"49020","buy":"48870"},"Canadian Dollar":{"sell":"33675","buy":"33575"},"Australian Dollar":{"sell":"31395","buy":"31295"},"Swedish Krona":{"sell":"4380","buy":"4365"},"Norwegian Krone":{"sell":"4605","buy":"4590"},"Russian Ruble":{"sell":"660","buy":"655"},"Thai Baht":{"sell":"1380","buy":"1375"},"Singapore Dollar":{"sell":"34175","buy":"34075"},"Hong Kong Dollar":{"sell":"5755","buy":"5725"},"Azerbaijani Manat":{"sell":"26465","buy":"26365"},"Armenian Dram":{"sell":"1140","buy":"1135"},"Danish Krone":{"sell":"6580","buy":"6560"},"UAE Dirham":{"sell":"12280","buy":"12260"},"Japanese Yen":{"sell":"3480","buy":"3470"},"Turkish Lira":{"sell":"2405","buy":"2385"},"Chinese Yuan":{"sell":"6650","buy":"6630"},"KSA Riyal":{"sell":"12015","buy":"11985"},"Indian Rupee":{"sell":"555","buy":"555"},"Ringgit":{"sell":"10525","buy":"10495"},"Afghan Afghani":{"sell":"505","buy":"500"},"Kuwaiti Dinar":{"sell":"147590","buy":"147190"},"Iraqi Dinar":{"sell":"3090","buy":"3080"},"Bahraini Dinar":{"sell":"119645","buy":"119145"},"Omani Rial":{"sell":"117145","buy":"116845"},"Qatari Riyal":{"sell":"12385","buy":"12355"},"Azadi":{"sell":"23600000","buy":"23100000"},"Emami":{"sell":"24950000","buy":"24650000"},"\u00bd Azadi":{"sell":"14800000","buy":"14500000"},"\u00bc Azadi":{"sell":"10300000","buy":"9800000"},"Gerami":{"sell":"5200000","buy":"4800000"},"Gold Gram":{"sell":"2119210"},"Gold Mithqal":{"sell":"9180000"},"Gold Ounce":{"sell":"1926.08"},"Bitcoin":{"sell":"22918.33"}}
