{"US Dollar":{"sell":"25830","buy":"25730"},"Euro":{"sell":"28400","buy":"28250"},"British Pound":{"sell":"33805","buy":"33605"},"Swiss Franc":{"sell":"27770","buy":"27620"},"Canadian Dollar":{"sell":"20200","buy":"20100"},"Australian Dollar":{"sell":"18960","buy":"18860"},"Swedish Krona":{"sell":"2660","buy":"2645"},"Norwegian Krone":{"sell":"2885","buy":"2870"},"Russian Ruble":{"sell":"192","buy":"189"},"Thai Baht":{"sell":"780","buy":"775"},"Singapore Dollar":{"sell":"19000","buy":"18900"},"Hong Kong Dollar":{"sell":"3300","buy":"3270"},"Azerbaijani Manat":{"sell":"15215","buy":"15115"},"Armenian Dram":{"sell":"495","buy":"490"},"Danish Krone":{"sell":"3815","buy":"3795"},"UAE Dirham":{"sell":"7030","buy":"7010"},"Japanese Yen":{"sell":"2220","buy":"2210"},"Turkish Lira":{"sell":"1735","buy":"1715"},"Chinese Yuan":{"sell":"4085","buy":"4065"},"KSA Riyal":{"sell":"6885","buy":"6855"},"Indian Rupee":{"sell":"338","buy":"336"},"Ringgit":{"sell":"6160","buy":"6130"},"Afghan Afghani":{"sell":"290","buy":"288"},"Kuwaiti Dinar":{"sell":"85065","buy":"84665"},"Iraqi Dinar":{"sell":"1760","buy":"1750"},"Bahraini Dinar":{"sell":"68510","buy":"68010"},"Omani Rial":{"sell":"67090","buy":"66790"},"Qatari Riyal":{"sell":"7095","buy":"7065"},"Azadi":{"sell":"12000000","buy":"11810000"},"Emami":{"sell":"12150000","buy":"11950000"},"\u00bd Azadi":{"sell":"7050000","buy":"6850000"},"\u00bc Azadi":{"sell":"4080000","buy":"3850000"},"Gerami":{"sell":"2450000","buy":"2300000"},"Gold Gram":{"sell":"1216353"},"Gold Mithqal":{"sell":"5269000"},"Gold Ounce":{"sell":"1988.78"},"Bitcoin":{"sell":"38460.89"}}
