{"US Dollar":{"sell":"25900","buy":"25800"},"Euro":{"sell":"28135","buy":"27985"},"British Pound":{"sell":"34115","buy":"33915"},"Swiss Franc":{"sell":"28015","buy":"27865"},"Canadian Dollar":{"sell":"20380","buy":"20280"},"Australian Dollar":{"sell":"19180","buy":"19080"},"Swedish Krona":{"sell":"2595","buy":"2580"},"Norwegian Krone":{"sell":"2880","buy":"2865"},"Russian Ruble":{"sell":"243","buy":"240"},"Thai Baht":{"sell":"785","buy":"780"},"Singapore Dollar":{"sell":"18985","buy":"18885"},"Hong Kong Dollar":{"sell":"3315","buy":"3285"},"Azerbaijani Manat":{"sell":"15270","buy":"15170"},"Armenian Dram":{"sell":"510","buy":"505"},"Danish Krone":{"sell":"3780","buy":"3760"},"UAE Dirham":{"sell":"7050","buy":"7030"},"Japanese Yen":{"sell":"2250","buy":"2240"},"Turkish Lira":{"sell":"1805","buy":"1785"},"Chinese Yuan":{"sell":"4100","buy":"4080"},"KSA Riyal":{"sell":"6900","buy":"6870"},"Indian Rupee":{"sell":"336","buy":"334"},"Ringgit":{"sell":"6200","buy":"6170"},"Afghan Afghani":{"sell":"284","buy":"282"},"Kuwaiti Dinar":{"sell":"85210","buy":"84810"},"Iraqi Dinar":{"sell":"1755","buy":"1745"},"Bahraini Dinar":{"sell":"68695","buy":"68195"},"Omani Rial":{"sell":"67365","buy":"67065"},"Qatari Riyal":{"sell":"7115","buy":"7085"},"Azadi":{"sell":"11850000","buy":"11650000"},"Emami":{"sell":"12050000","buy":"11900000"},"\u00bd Azadi":{"sell":"6850000","buy":"6700000"},"\u00bc Azadi":{"sell":"3880000","buy":"3780000"},"Gerami":{"sell":"2350000","buy":"2250000"},"Gold Gram":{"sell":"1210582"},"Gold Mithqal":{"sell":"5244000"},"Gold Ounce":{"sell":"1996.24"},"Bitcoin":{"sell":"38154.09"}}
