{"US Dollar":{"sell":"38520","buy":"38420"},"Euro":{"sell":"40910","buy":"40760"},"British Pound":{"sell":"47530","buy":"47330"},"Swiss Franc":{"sell":"41460","buy":"41310"},"Canadian Dollar":{"sell":"28375","buy":"28275"},"Australian Dollar":{"sell":"26085","buy":"25985"},"Swedish Krona":{"sell":"3750","buy":"3735"},"Norwegian Krone":{"sell":"3925","buy":"3910"},"Russian Ruble":{"sell":"600","buy":"595"},"Thai Baht":{"sell":"1105","buy":"1100"},"Singapore Dollar":{"sell":"28430","buy":"28330"},"Hong Kong Dollar":{"sell":"4950","buy":"4920"},"Azerbaijani Manat":{"sell":"22915","buy":"22815"},"Armenian Dram":{"sell":"970","buy":"965"},"Danish Krone":{"sell":"5500","buy":"5480"},"UAE Dirham":{"sell":"10490","buy":"10470"},"Japanese Yen":{"sell":"2820","buy":"2810"},"Turkish Lira":{"sell":"2065","buy":"2045"},"Chinese Yuan":{"sell":"5520","buy":"5500"},"KSA Riyal":{"sell":"10245","buy":"10215"},"Indian Rupee":{"sell":"465","buy":"463"},"Ringgit":{"sell":"8720","buy":"8690"},"Afghan Afghani":{"sell":"445","buy":"443"},"Kuwaiti Dinar":{"sell":"125640","buy":"125240"},"Iraqi Dinar":{"sell":"2640","buy":"2630"},"Bahraini Dinar":{"sell":"102190","buy":"101690"},"Omani Rial":{"sell":"100055","buy":"99755"},"Qatari Riyal":{"sell":"10580","buy":"10550"},"Azadi":{"sell":"17950000","buy":"17600000"},"Emami":{"sell":"19100000","buy":"18800000"},"\u00bd Azadi":{"sell":"11950000","buy":"11650000"},"\u00bc Azadi":{"sell":"8950000","buy":"8700000"},"Gerami":{"sell":"4200000","buy":"4000000"},"Gold Gram":{"sell":"1693752"},"Gold Mithqal":{"sell":"7337000"},"Gold Ounce":{"sell":"1778.72"},"Bitcoin":{"sell":"17705.21"}}
