{"US Dollar":{"sell":"35420","buy":"35320"},"Euro":{"sell":"36420","buy":"36270"},"British Pound":{"sell":"41910","buy":"41710"},"Swiss Franc":{"sell":"37065","buy":"36915"},"Canadian Dollar":{"sell":"26410","buy":"26310"},"Australian Dollar":{"sell":"23550","buy":"23450"},"Swedish Krona":{"sell":"3310","buy":"3295"},"Norwegian Krone":{"sell":"3460","buy":"3445"},"Russian Ruble":{"sell":"585","buy":"580"},"Thai Baht":{"sell":"980","buy":"975"},"Singapore Dollar":{"sell":"25700","buy":"25600"},"Hong Kong Dollar":{"sell":"4535","buy":"4505"},"Azerbaijani Manat":{"sell":"20735","buy":"20635"},"Armenian Dram":{"sell":"890","buy":"885"},"Danish Krone":{"sell":"4895","buy":"4875"},"UAE Dirham":{"sell":"9645","buy":"9625"},"Japanese Yen":{"sell":"2520","buy":"2510"},"Turkish Lira":{"sell":"1905","buy":"1885"},"Chinese Yuan":{"sell":"4950","buy":"4930"},"KSA Riyal":{"sell":"9420","buy":"9390"},"Indian Rupee":{"sell":"433","buy":"431"},"Ringgit":{"sell":"7745","buy":"7715"},"Afghan Afghani":{"sell":"397","buy":"395"},"Kuwaiti Dinar":{"sell":"115075","buy":"114675"},"Iraqi Dinar":{"sell":"2415","buy":"2405"},"Bahraini Dinar":{"sell":"93485","buy":"92985"},"Omani Rial":{"sell":"91875","buy":"91575"},"Qatari Riyal":{"sell":"9730","buy":"9700"},"Azadi":{"sell":"15500000","buy":"15150000"},"Emami":{"sell":"16250000","buy":"16000000"},"\u00bd Azadi":{"sell":"8850000","buy":"8600000"},"\u00bc Azadi":{"sell":"5850000","buy":"5600000"},"Gerami":{"sell":"3250000","buy":"3100000"},"Gold Gram":{"sell":"1492220"},"Gold Mithqal":{"sell":"6464000"},"Gold Ounce":{"sell":"1745.39"},"Bitcoin":{"sell":"16088.3"}}
