{"US Dollar":{"sell":"31680","buy":"31580"},"Euro":{"sell":"30505","buy":"30355"},"British Pound":{"sell":"34220","buy":"34020"},"Swiss Franc":{"sell":"32090","buy":"31940"},"Canadian Dollar":{"sell":"23150","buy":"23050"},"Australian Dollar":{"sell":"20565","buy":"20465"},"Swedish Krona":{"sell":"2810","buy":"2795"},"Norwegian Krone":{"sell":"2950","buy":"2935"},"Russian Ruble":{"sell":"545","buy":"545"},"Thai Baht":{"sell":"835","buy":"830"},"Singapore Dollar":{"sell":"22070","buy":"21970"},"Hong Kong Dollar":{"sell":"4035","buy":"4005"},"Azerbaijani Manat":{"sell":"18670","buy":"18570"},"Armenian Dram":{"sell":"765","buy":"760"},"Danish Krone":{"sell":"4100","buy":"4080"},"UAE Dirham":{"sell":"8625","buy":"8605"},"Japanese Yen":{"sell":"2195","buy":"2185"},"Turkish Lira":{"sell":"1715","buy":"1695"},"Chinese Yuan":{"sell":"4415","buy":"4395"},"KSA Riyal":{"sell":"8425","buy":"8395"},"Indian Rupee":{"sell":"388","buy":"386"},"Ringgit":{"sell":"6870","buy":"6840"},"Afghan Afghani":{"sell":"358","buy":"356"},"Kuwaiti Dinar":{"sell":"101975","buy":"101575"},"Iraqi Dinar":{"sell":"2170","buy":"2160"},"Bahraini Dinar":{"sell":"84020","buy":"83520"},"Omani Rial":{"sell":"82385","buy":"82085"},"Qatari Riyal":{"sell":"8700","buy":"8670"},"Azadi":{"sell":"13500000","buy":"13200000"},"Emami":{"sell":"14350000","buy":"14150000"},"\u00bd Azadi":{"sell":"8000000","buy":"7850000"},"\u00bc Azadi":{"sell":"5000000","buy":"4850000"},"Gerami":{"sell":"3030000","buy":"2930000"},"Gold Gram":{"sell":"1306616"},"Gold Mithqal":{"sell":"5660000"},"Gold Ounce":{"sell":"1639.6"},"Bitcoin":{"sell":"20296.11"}}
