{"US Dollar":{"sell":"32100","buy":"32000"},"Euro":{"sell":"33735","buy":"33585"},"British Pound":{"sell":"39290","buy":"39090"},"Swiss Franc":{"sell":"33230","buy":"33080"},"Canadian Dollar":{"sell":"24755","buy":"24655"},"Australian Dollar":{"sell":"22220","buy":"22120"},"Swedish Krona":{"sell":"3165","buy":"3150"},"Norwegian Krone":{"sell":"3245","buy":"3230"},"Russian Ruble":{"sell":"595","buy":"595"},"Thai Baht":{"sell":"905","buy":"900"},"Singapore Dollar":{"sell":"23130","buy":"23030"},"Hong Kong Dollar":{"sell":"4090","buy":"4060"},"Azerbaijani Manat":{"sell":"18920","buy":"18820"},"Armenian Dram":{"sell":"760","buy":"755"},"Danish Krone":{"sell":"4535","buy":"4515"},"UAE Dirham":{"sell":"8740","buy":"8720"},"Japanese Yen":{"sell":"2355","buy":"2345"},"Turkish Lira":{"sell":"1850","buy":"1830"},"Chinese Yuan":{"sell":"4780","buy":"4760"},"KSA Riyal":{"sell":"8555","buy":"8525"},"Indian Rupee":{"sell":"410","buy":"408"},"Ringgit":{"sell":"7290","buy":"7260"},"Afghan Afghani":{"sell":"358","buy":"356"},"Kuwaiti Dinar":{"sell":"104535","buy":"104135"},"Iraqi Dinar":{"sell":"2190","buy":"2180"},"Bahraini Dinar":{"sell":"85140","buy":"84640"},"Omani Rial":{"sell":"83380","buy":"83080"},"Qatari Riyal":{"sell":"8815","buy":"8785"},"Azadi":{"sell":"14700000","buy":"14400000"},"Emami":{"sell":"15650000","buy":"15400000"},"\u00bd Azadi":{"sell":"8500000","buy":"8300000"},"\u00bc Azadi":{"sell":"5470000","buy":"5270000"},"Gerami":{"sell":"3050000","buy":"2950000"},"Gold Gram":{"sell":"1442125"},"Gold Mithqal":{"sell":"6247000"},"Gold Ounce":{"sell":"1825.49"},"Bitcoin":{"sell":"20414.81"}}
