{"US Dollar":{"sell":"32100","buy":"32000"},"Euro":{"sell":"32400","buy":"32250"},"British Pound":{"sell":"38165","buy":"37965"},"Swiss Franc":{"sell":"32900","buy":"32750"},"Canadian Dollar":{"sell":"24700","buy":"24600"},"Australian Dollar":{"sell":"21845","buy":"21745"},"Swedish Krona":{"sell":"3065","buy":"3050"},"Norwegian Krone":{"sell":"3160","buy":"3145"},"Russian Ruble":{"sell":"560","buy":"560"},"Thai Baht":{"sell":"875","buy":"870"},"Singapore Dollar":{"sell":"22970","buy":"22870"},"Hong Kong Dollar":{"sell":"4090","buy":"4060"},"Azerbaijani Manat":{"sell":"18820","buy":"18720"},"Armenian Dram":{"sell":"780","buy":"775"},"Danish Krone":{"sell":"4355","buy":"4335"},"UAE Dirham":{"sell":"8740","buy":"8720"},"Japanese Yen":{"sell":"2320","buy":"2310"},"Turkish Lira":{"sell":"1845","buy":"1825"},"Chinese Yuan":{"sell":"4760","buy":"4740"},"KSA Riyal":{"sell":"8550","buy":"8520"},"Indian Rupee":{"sell":"402","buy":"400"},"Ringgit":{"sell":"7210","buy":"7180"},"Afghan Afghani":{"sell":"366","buy":"364"},"Kuwaiti Dinar":{"sell":"104210","buy":"103810"},"Iraqi Dinar":{"sell":"2205","buy":"2195"},"Bahraini Dinar":{"sell":"85430","buy":"84930"},"Omani Rial":{"sell":"83390","buy":"83090"},"Qatari Riyal":{"sell":"8815","buy":"8785"},"Azadi":{"sell":"14350000","buy":"13950000"},"Emami":{"sell":"15050000","buy":"14800000"},"\u00bd Azadi":{"sell":"8250000","buy":"8050000"},"\u00bc Azadi":{"sell":"5250000","buy":"5050000"},"Gerami":{"sell":"3050000","buy":"2900000"},"Gold Gram":{"sell":"1365944"},"Gold Mithqal":{"sell":"5917000"},"Gold Ounce":{"sell":"1718.85"},"Bitcoin":{"sell":"22204.76"}}
