{"US Dollar":{"sell":"32250","buy":"32150"},"Euro":{"sell":"33920","buy":"33770"},"British Pound":{"sell":"39715","buy":"39515"},"Swiss Franc":{"sell":"32640","buy":"32490"},"Canadian Dollar":{"sell":"25265","buy":"25165"},"Australian Dollar":{"sell":"22800","buy":"22700"},"Swedish Krona":{"sell":"3225","buy":"3210"},"Norwegian Krone":{"sell":"3325","buy":"3310"},"Russian Ruble":{"sell":"560","buy":"560"},"Thai Baht":{"sell":"930","buy":"925"},"Singapore Dollar":{"sell":"23235","buy":"23135"},"Hong Kong Dollar":{"sell":"4110","buy":"4080"},"Azerbaijani Manat":{"sell":"18925","buy":"18825"},"Armenian Dram":{"sell":"765","buy":"760"},"Danish Krone":{"sell":"4560","buy":"4540"},"UAE Dirham":{"sell":"8780","buy":"8760"},"Japanese Yen":{"sell":"2400","buy":"2390"},"Turkish Lira":{"sell":"1885","buy":"1865"},"Chinese Yuan":{"sell":"4805","buy":"4785"},"KSA Riyal":{"sell":"8600","buy":"8570"},"Indian Rupee":{"sell":"412","buy":"410"},"Ringgit":{"sell":"7325","buy":"7295"},"Afghan Afghani":{"sell":"362","buy":"360"},"Kuwaiti Dinar":{"sell":"105135","buy":"104735"},"Iraqi Dinar":{"sell":"2210","buy":"2200"},"Bahraini Dinar":{"sell":"85570","buy":"85070"},"Omani Rial":{"sell":"83770","buy":"83470"},"Qatari Riyal":{"sell":"8855","buy":"8825"},"Azadi":{"sell":"14700000","buy":"14500000"},"Emami":{"sell":"14940000","buy":"14880000"},"\u00bd Azadi":{"sell":"8520000","buy":"8450000"},"\u00bc Azadi":{"sell":"5520000","buy":"5450000"},"Gerami":{"sell":"3030000","buy":"2950000"},"Gold Gram":{"sell":"1468211"},"Gold Mithqal":{"sell":"6360000"},"Gold Ounce":{"sell":"1871.61"},"Bitcoin":{"sell":"29242.49"}}
