{"US Dollar":{"sell":"38500","buy":"38400"},"Euro":{"sell":"41155","buy":"41005"},"British Pound":{"sell":"47845","buy":"47645"},"Swiss Franc":{"sell":"41640","buy":"41490"},"Canadian Dollar":{"sell":"28510","buy":"28410"},"Australian Dollar":{"sell":"26515","buy":"26415"},"Swedish Krona":{"sell":"3785","buy":"3770"},"Norwegian Krone":{"sell":"3965","buy":"3950"},"Russian Ruble":{"sell":"610","buy":"605"},"Thai Baht":{"sell":"1115","buy":"1110"},"Singapore Dollar":{"sell":"28670","buy":"28570"},"Hong Kong Dollar":{"sell":"4965","buy":"4935"},"Azerbaijani Manat":{"sell":"22715","buy":"22615"},"Armenian Dram":{"sell":"985","buy":"980"},"Danish Krone":{"sell":"5535","buy":"5515"},"UAE Dirham":{"sell":"10510","buy":"10490"},"Japanese Yen":{"sell":"2855","buy":"2845"},"Turkish Lira":{"sell":"2070","buy":"2050"},"Chinese Yuan":{"sell":"5555","buy":"5535"},"KSA Riyal":{"sell":"10265","buy":"10235"},"Indian Rupee":{"sell":"468","buy":"466"},"Ringgit":{"sell":"8790","buy":"8760"},"Afghan Afghani":{"sell":"448","buy":"446"},"Kuwaiti Dinar":{"sell":"125940","buy":"125540"},"Iraqi Dinar":{"sell":"2670","buy":"2660"},"Bahraini Dinar":{"sell":"102380","buy":"101880"},"Omani Rial":{"sell":"100255","buy":"99955"},"Qatari Riyal":{"sell":"10600","buy":"10570"},"Azadi":{"sell":"18600000","buy":"18300000"},"Emami":{"sell":"19600000","buy":"19250000"},"\u00bd Azadi":{"sell":"12250000","buy":"11950000"},"\u00bc Azadi":{"sell":"9250000","buy":"8950000"},"Gerami":{"sell":"4350000","buy":"4100000"},"Gold Gram":{"sell":"1672052"},"Gold Mithqal":{"sell":"7243000"},"Gold Ounce":{"sell":"1807.4"},"Bitcoin":{"sell":"17824.01"}}
