{"US Dollar":{"sell":"42100","buy":"42000"},"Euro":{"sell":"44955","buy":"44805"},"British Pound":{"sell":"50685","buy":"50485"},"Swiss Franc":{"sell":"45635","buy":"45485"},"Canadian Dollar":{"sell":"31130","buy":"31030"},"Australian Dollar":{"sell":"28625","buy":"28525"},"Swedish Krona":{"sell":"4060","buy":"4045"},"Norwegian Krone":{"sell":"4280","buy":"4265"},"Russian Ruble":{"sell":"590","buy":"585"},"Thai Baht":{"sell":"1220","buy":"1215"},"Singapore Dollar":{"sell":"31415","buy":"31315"},"Hong Kong Dollar":{"sell":"5400","buy":"5370"},"Azerbaijani Manat":{"sell":"24755","buy":"24655"},"Armenian Dram":{"sell":"1070","buy":"1065"},"Danish Krone":{"sell":"6045","buy":"6025"},"UAE Dirham":{"sell":"11465","buy":"11445"},"Japanese Yen":{"sell":"3195","buy":"3185"},"Turkish Lira":{"sell":"2250","buy":"2230"},"Chinese Yuan":{"sell":"6100","buy":"6080"},"KSA Riyal":{"sell":"11190","buy":"11160"},"Indian Rupee":{"sell":"510","buy":"510"},"Ringgit":{"sell":"9555","buy":"9525"},"Afghan Afghani":{"sell":"474","buy":"469"},"Kuwaiti Dinar":{"sell":"137560","buy":"137160"},"Iraqi Dinar":{"sell":"2890","buy":"2880"},"Bahraini Dinar":{"sell":"111660","buy":"111160"},"Omani Rial":{"sell":"109345","buy":"109045"},"Qatari Riyal":{"sell":"11560","buy":"11530"},"Azadi":{"sell":"21000000","buy":"20000000"},"Emami":{"sell":"23000000","buy":"22500000"},"\u00bd Azadi":{"sell":"13000000","buy":"12700000"},"\u00bc Azadi":{"sell":"10000000","buy":"9600000"},"Gerami":{"sell":"4700000","buy":"4300000"},"Gold Gram":{"sell":"1920679"},"Gold Mithqal":{"sell":"8320000"},"Gold Ounce":{"sell":"1819.58"},"Bitcoin":{"sell":"16485.3"}}
