{"US Dollar":{"sell":"29900","buy":"29800"},"Euro":{"sell":"30450","buy":"30300"},"British Pound":{"sell":"36245","buy":"36045"},"Swiss Franc":{"sell":"31510","buy":"31360"},"Canadian Dollar":{"sell":"23290","buy":"23190"},"Australian Dollar":{"sell":"20975","buy":"20875"},"Swedish Krona":{"sell":"2895","buy":"2880"},"Norwegian Krone":{"sell":"3095","buy":"3080"},"Russian Ruble":{"sell":"490","buy":"490"},"Thai Baht":{"sell":"845","buy":"840"},"Singapore Dollar":{"sell":"21695","buy":"21595"},"Hong Kong Dollar":{"sell":"3815","buy":"3785"},"Azerbaijani Manat":{"sell":"17600","buy":"17500"},"Armenian Dram":{"sell":"745","buy":"740"},"Danish Krone":{"sell":"4095","buy":"4075"},"UAE Dirham":{"sell":"8140","buy":"8120"},"Japanese Yen":{"sell":"2230","buy":"2220"},"Turkish Lira":{"sell":"1665","buy":"1645"},"Chinese Yuan":{"sell":"4415","buy":"4395"},"KSA Riyal":{"sell":"7965","buy":"7935"},"Indian Rupee":{"sell":"377","buy":"375"},"Ringgit":{"sell":"6695","buy":"6665"},"Afghan Afghani":{"sell":"338","buy":"336"},"Kuwaiti Dinar":{"sell":"97465","buy":"97065"},"Iraqi Dinar":{"sell":"2055","buy":"2045"},"Bahraini Dinar":{"sell":"79310","buy":"78810"},"Omani Rial":{"sell":"77665","buy":"77365"},"Qatari Riyal":{"sell":"8210","buy":"8180"},"Azadi":{"sell":"12950000","buy":"12650000"},"Emami":{"sell":"13950000","buy":"13700000"},"\u00bd Azadi":{"sell":"7850000","buy":"7600000"},"\u00bc Azadi":{"sell":"4900000","buy":"4650000"},"Gerami":{"sell":"2950000","buy":"2800000"},"Gold Gram":{"sell":"1301999"},"Gold Mithqal":{"sell":"5640000"},"Gold Ounce":{"sell":"1777.68"},"Bitcoin":{"sell":"24400.48"}}
