{"US Dollar":{"sell":"30800","buy":"30700"},"Euro":{"sell":"31275","buy":"31125"},"British Pound":{"sell":"35730","buy":"35530"},"Swiss Franc":{"sell":"32115","buy":"31965"},"Canadian Dollar":{"sell":"23615","buy":"23515"},"Australian Dollar":{"sell":"21095","buy":"20995"},"Swedish Krona":{"sell":"2895","buy":"2880"},"Norwegian Krone":{"sell":"3100","buy":"3085"},"Russian Ruble":{"sell":"500","buy":"500"},"Thai Baht":{"sell":"845","buy":"840"},"Singapore Dollar":{"sell":"22020","buy":"21920"},"Hong Kong Dollar":{"sell":"3925","buy":"3895"},"Azerbaijani Manat":{"sell":"18075","buy":"17975"},"Armenian Dram":{"sell":"765","buy":"760"},"Danish Krone":{"sell":"4160","buy":"4140"},"UAE Dirham":{"sell":"8385","buy":"8365"},"Japanese Yen":{"sell":"2160","buy":"2150"},"Turkish Lira":{"sell":"1690","buy":"1670"},"Chinese Yuan":{"sell":"4445","buy":"4425"},"KSA Riyal":{"sell":"8195","buy":"8165"},"Indian Rupee":{"sell":"386","buy":"384"},"Ringgit":{"sell":"6845","buy":"6815"},"Afghan Afghani":{"sell":"351","buy":"349"},"Kuwaiti Dinar":{"sell":"99860","buy":"99460"},"Iraqi Dinar":{"sell":"2125","buy":"2115"},"Bahraini Dinar":{"sell":"82330","buy":"81830"},"Omani Rial":{"sell":"79995","buy":"79695"},"Qatari Riyal":{"sell":"8460","buy":"8430"},"Azadi":{"sell":"13400000","buy":"13150000"},"Emami":{"sell":"14100000","buy":"13920000"},"\u00bd Azadi":{"sell":"8020000","buy":"7890000"},"\u00bc Azadi":{"sell":"5030000","buy":"4920000"},"Gerami":{"sell":"2980000","buy":"2900000"},"Gold Gram":{"sell":"1308924"},"Gold Mithqal":{"sell":"5670000"},"Gold Ounce":{"sell":"1717.32"},"Bitcoin":{"sell":"21541.08"}}
